nmosquery/__init__.py
nmosquery/api.py
nmosquery/changewatcher.py
nmosquery/config.py
nmosquery/etcd_backend.py
nmosquery/etcd_util.py
nmosquery/etcd_watch.py
nmosquery/grainevent.py
nmosquery/service.py
nmosquery/util.py
nmosquery/common/__init__.py
nmosquery/common/query.py
nmosquery/common/querysockets.py
nmosquery/common/routes.py
nmosquery/v1_0/__init__.py
nmosquery/v1_0/query.py
nmosquery/v1_0/querysockets.py
nmosquery/v1_0/routes.py
nmosquery/v1_1/__init__.py
nmosquery/v1_1/query.py
nmosquery/v1_1/querysockets.py
nmosquery/v1_1/routes.py
nmosquery/v1_2/__init__.py
nmosquery/v1_2/query.py
nmosquery/v1_2/querysockets.py
nmosquery/v1_2/routes.py
nmosquery/v1_3/__init__.py
nmosquery/v1_3/query.py
nmosquery/v1_3/querysockets.py
nmosquery/v1_3/routes.py
tests/__init__.py
tests/test_api.py
tests/test_changewatcher.py
tests/test_util.py
tests/common/__init__.py
tests/common/test_query.py
tests/v1_0/__init__.py
tests/v1_0/test_query.py
tests/v1_1/__init__.py
tests/v1_1/test_query.py
tests/v1_2/__init__.py
tests/v1_2/test_query.py
tests/v1_3/__init__.py
tests/v1_3/test_query.py
usr/bin/nmosquery
registryquery-0.8.3.dist-info/LICENSE.md
registryquery-0.8.3.dist-info/METADATA
registryquery-0.8.3.dist-info/WHEEL
registryquery-0.8.3.dist-info/top_level.txt
registryquery-0.8.3.dist-info/RECORD
