Metadata-Version: 1.0
Name: registryquery
Version: 0.8.3
Summary: BBC implementation of an AMWA NMOS Query API
Home-page: https://github.com/bbc/nmos-query
Author: Peter Brightwell
Author-email: peter.brightwell@bbc.co.uk
License: Apache 2
Platform: UNKNOWN
